{
  "106": "FLAMEBODY",
  "170": "LIQUIDOOZE",
  "182": "GUARDDOG",
  "114": "SCHOOLING",
  "168": "MOLDBREAKER",
  "24": "ARENATRAP",
  "277": "SHELLARMOR",
  "223": "JUSTIFIED",
  "93": "QUICKDRAW",
  "225": "SNOWWARNING",
  "144": "OBLIVIOUS",
  "235": "IMPOSTER",
  "112": "HUGEPOWER",
  "206": "FOREWARN",
  "162": "STEELWORKER",
  "251": "PERISHBODY",
  "163": "COMATOSE",
  "183": "HEATPROOF",
  "213": "TANGLINGHAIR",
  "31": "FRIENDGUARD",
  "52": "ANGERPOINT",
  "104": "SANDSTREAM",
  "263": "UNSEENFIST",
  "66": "LONGREACH",
  "38": "ASONEGLASTRIER",
  "306": "TABLETSOFRUIN",
  "152": "STATIC",
  "267": "SCRAPPY",
  "315": "ZEROTOHERO",
  "73": "SLUSHRUSH",
  "187": "SHIELDDUST",
  "207": "IRONBARBS",
  "287": "EMBODYASPECTCORNERSTONE",
  "13": "RKSSYSTEM",
  "126": "FAIRYAURA",
  "71": "MOXIE",
  "282": "PERSISTENT",
  "45": "SWIFTSWIM",
  "120": "HARVEST",
  "181": "SPEEDBOOST",
  "86": "LIBERO",
  "238": "UNBURDEN",
  "32": "NOABILITY",
  "49": "INSOMNIA",
  "72": "SAPSIPPER",
  "113": "SOLARPOWER",
  "175": "COMPETITIVE",
  "108": "PRESSURE",
  "228": "WIMPOUT",
  "278": "RATTLED",
  "215": "STEELYSPIRIT",
  "226": "FLOWERGIFT",
  "146": "LEVITATE",
  "149": "ICEBODY",
  "294": "CUDCHEW",
  "244": "SANDVEIL",
  "298": "HOSPITALITY",
  "115": "MOTORDRIVE",
  "43": "INTREPIDSWORD",
  "111": "LEAFGUARD",
  "125": "WATERVEIL",
  "311": "TOXICCHAIN",
  "301": "POISONPUPPETEER",
  "178": "ILLUMINATE",
  "147": "ASONESPECTRIER",
  "272": "DRIZZLE",
  "68": "TINTEDLENS",
  "145": "SURGESURFER",
  "100": "EFFECTSPORE",
  "5": "CLEARBODY",
  "161": "COMPOUNDEYES",
  "103": "MAGICGUARD",
  "50": "DANCER",
  "304": "SUPERSWEETSYRUP",
  "1": "ARMORTAIL",
  "22": "TECHNICIAN",
  "157": "GLUTTONY",
  "158": "KEENEYE",
  "164": "BALLFETCH",
  "214": "CLOUDNINE",
  "51": "STEAMENGINE",
  "82": "NOGUARD",
  "261": "IRONFIST",
  "281": "TOXICBOOST",
  "284": "SIMPLE",
  "265": "HUSTLE",
  "153": "WONDERSKIN",
  "176": "SWARM",
  "166": "DOWNLOAD",
  "250": "DAMP",
  "85": "KLUTZ",
  "299": "LINGERINGAROMA",
  "123": "ROUGHSKIN",
  "3": "TANGLEDFEET",
  "186": "CHILLINGNEIGH",
  "59": "ILLUSION",
  "208": "STAMINA",
  "307": "TERASHELL",
  "268": "MINDSEYE",
  "312": "VESSELOFRUIN",
  "203": "FURCOAT",
  "232": "PSYCHICSURGE",
  "140": "ELECTRICSURGE",
  "98": "PASTELVEIL",
  "236": "DRYSKIN",
  "210": "COLORCHANGE",
  "292": "COMMANDER",
  "128": "SEEDSOWER",
  "135": "DARKAURA",
  "23": "MULTISCALE",
  "241": "MOODY",
  "26": "DISGUISE",
  "136": "VICTORYSTAR",
  "222": "WATERCOMPACTION",
  "62": "INNARDSOUT",
  "276": "GUTS",
  "291": "BEADSOFRUIN",
  "302": "PROTOSYNTHESIS",
  "305": "SWORDOFRUIN",
  "288": "EMBODYASPECTHEARTHFLAME",
  "37": "PROTEAN",
  "177": "STALWART",
  "270": "NEUTRALIZINGGAS",
  "260": "GRIMNEIGH",
  "202": "TRUANT",
  "122": "ICEFACE",
  "134": "NORMALIZE",
  "197": "BERSERK",
  "141": "HADRONENGINE",
  "78": "SHADOWSHIELD",
  "21": "POWEROFALCHEMY",
  "42": "SKILLLINK",
  "154": "OVERGROW",
  "77": "FLAREBOOST",
  "257": "GALEWINGS",
  "17": "ROCKHEAD",
  "271": "SWEETVEIL",
  "290": "ANGERSHELL",
  "54": "MAGMAARMOR",
  "171": "POISONHEAL",
  "194": "GRASSPELT",
  "191": "MAGNETPULL",
  "53": "CONTRARY",
  "127": "SANDSPIT",
  "234": "WATERABSORB",
  "286": "EMBODYASPECTWELLSPRING",
  "29": "MAGICIAN",
  "61": "DROUGHT",
  "242": "ROCKYPAYLOAD",
  "34": "POWERCONSTRUCT",
  "204": "FULLMETALBODY",
  "89": "UNAWARE",
  "309": "TERAFORMZERO",
  "196": "BEASTBOOST",
  "63": "SHIELDSDOWN",
  "116": "ANTICIPATION",
  "16": "UNNERVE",
  "117": "MERCILESS",
  "99": "TOUGHCLAWS",
  "15": "STAKEOUT",
  "55": "HUNGERSWITCH",
  "65": "CORROSION",
  "107": "RECKLESS",
  "172": "PRISMARMOR",
  "83": "TORRENT",
  "102": "BADDREAMS",
  "221": "PIXILATE",
  "247": "BATTERY",
  "262": "REBOUND",
  "192": "HONEYGATHER",
  "48": "SUPREMEOVERLORD",
  "159": "MOUNTAINEER",
  "205": "REGENERATOR",
  "97": "MIRRORARMOR",
  "216": "QUICKFEET",
  "118": "TRACE",
  "190": "SCREENCLEANER",
  "41": "WINDRIDER",
  "289": "EMBODYASPECTTEAL",
  "212": "ANALYTIC",
  "218": "MEGALAUNCHER",
  "27": "EARLYBIRD",
  "9": "DEFIANT",
  "249": "STEADFAST",
  "266": "HYDRATION",
  "274": "POISONTOUCH",
  "88": "CURSEDBODY",
  "96": "PLUS",
  "303": "QUARKDRIVE",
  "81": "MULTITYPE",
  "230": "INFILTRATOR",
  "308": "TERASHIFT",
  "56": "RECEIVER",
  "150": "CURIOUSMEDICINE",
  "121": "SUCTIONCUPS",
  "259": "STICKYHOLD",
  "36": "PRANKSTER",
  "131": "DAUNTLESSSHIELD",
  "47": "SUPERLUCK",
  "70": "DESOLATELAND",
  "12": "SOUNDPROOF",
  "155": "PROPELLERTAIL",
  "75": "STALL",
  "160": "FLASHFIRE",
  "200": "SYNCHRONIZE",
  "130": "INTIMIDATE",
  "8": "AERILATE",
  "87": "SERENEGRACE",
  "2": "RIPEN",
  "227": "SHEDSKIN",
  "4": "DRAGONSMAW",
  "124": "WONDERGUARD",
  "46": "EARTHEATER",
  "173": "SNIPER",
  "297": "GOODASGOLD",
  "64": "ADAPTABILITY",
  "44": "SOULHEART",
  "95": "SYMBIOSIS",
  "129": "TOXICDEBRIS",
  "57": "ZENMODE",
  "60": "WEAKARMOR",
  "92": "TELEPATHY",
  "198": "MINUS",
  "79": "LIQUIDVOICE",
  "217": "MAGICBOUNCE",
  "220": "STORMDRAIN",
  "283": "CHLOROPHYLL",
  "237": "FLUFFY",
  "20": "BULLETPROOF",
  "30": "REFRIGERATE",
  "109": "GOOEY",
  "0": "NONE",
  "10": "CUTECHARM",
  "293": "COSTAR",
  "14": "POISONPOINT",
  "33": "GULPMISSILE",
  "233": "DEFEATIST",
  "138": "STURDY",
  "254": "OWNTEMPO",
  "179": "TURBOBLAZE",
  "91": "MARVELSCALE",
  "188": "RIVALRY",
  "74": "BIGPECKS",
  "184": "SNOWCLOAK",
  "285": "PURIFYINGSALT",
  "273": "INNERFOCUS",
  "169": "MYCELIUMMIGHT",
  "224": "SLOWSTART",
  "252": "TRIAGE",
  "148": "PICKUP",
  "199": "RAINDISH",
  "243": "PUNKROCK",
  "19": "MIMICRY",
  "119": "NATURALCURE",
  "156": "THICKFAT",
  "310": "THERMALEXCHANGE",
  "18": "AURABREAK",
  "201": "FILTER",
  "84": "DELTASTREAM",
  "219": "HEAVYMETAL",
  "67": "PUREPOWER",
  "248": "HEALER",
  "165": "DAZZLING",
  "180": "GORILLATACTICS",
  "255": "FRISK",
  "132": "AROMAVEIL",
  "300": "OPPORTUNIST",
  "39": "SHADOWTAG",
  "25": "BATTLEBOND",
  "245": "PARENTALBOND",
  "295": "ELECTROMORPHOSIS",
  "174": "STENCH",
  "211": "BLAZE",
  "246": "STRONGJAW",
  "193": "COTTONDOWN",
  "231": "LIMBER",
  "11": "NEUROFORCE",
  "58": "EMERGENCYEXIT",
  "137": "GRASSYSURGE",
  "253": "SHEERFORCE",
  "28": "LIGHTNINGROD",
  "142": "ORICHALCUMPULSE",
  "40": "SHARPNESS",
  "7": "VITALSPIRIT",
  "101": "MUMMY",
  "69": "QUEENLYMAJESTY",
  "105": "POWERSPOT",
  "80": "MISTYSURGE",
  "143": "RUNAWAY",
  "279": "WATERBUBBLE",
  "240": "STANCECHANGE",
  "139": "PICKPOCKET",
  "151": "FLOWERVEIL",
  "280": "SANDFORCE",
  "269": "OVERCOAT",
  "313": "WELLBAKEDBODY",
  "314": "WINDPOWER",
  "110": "IMMUNITY",
  "167": "TRANSISTOR",
  "189": "PRIMORDIALSEA",
  "229": "ICESCALES",
  "239": "CHEEKPOUCH",
  "185": "TERAVOLT",
  "195": "BATTLEARMOR",
  "209": "SANDRUSH",
  "256": "VOLTABSORB",
  "76": "WHITESMOKE",
  "35": "FORECAST",
  "264": "SOLIDROCK",
  "133": "AIRLOCK",
  "6": "GALVANIZE",
  "258": "AFTERMATH",
  "275": "WANDERINGSPIRIT",
  "90": "LIGHTMETAL",
  "94": "HYPERCUTTER",
  "296": "EMBODYASPECT"
}